[
  {
    "defaults": {
      "link": {
        "create": true,
        "relink": true
      }
    }
  },
  {
    "clean": ["~"]
  },
  {
    "link": {
      "~/.config/awesome": "config/awesome",
      "~/.config/compton.conf": "config/compton.conf",
      "~/.config/termite": "config/termite",
      "~/.local/share/oh-my-zsh": "local/share/oh-my-zsh",
      "~/.local/share/zsh-custom": "local/share/zsh-custom",
      "~/.vim": "vim",
      "~/.vimrc": "vimrc",
      "~/.Xresources": "Xresources",
      "~/.zshrc": "zshrc"
    }
  },
  {
    "shell": [
      ["git submodule update --init --recursive", "Installing submodules"]
    ]
  }
]
